{"success": true, "data": [{"team": {"id": 54, "name": "NestingDoll"}, "id": 14, "date": "2022-07-30T00:00:52+00:00", "user": {"id": 671, "name": "w0152"}, "challenge_id": 203, "challenge": {"id": 203, "value": 1, "category": "misc", "name": "Join Discord"}, "type": "correct"}, {"team": {"id": 54, "name": "NestingDoll"}, "id": 50, "date": "2022-07-30T00:05:34+00:00", "user": {"id": 676, "name": "oreosec"}, "challenge_id": 174, "challenge": {"id": 174, "value": 50, "category": "web", "name": "Frame"}, "type": "correct"}, {"team": {"id": 54, "name": "NestingDoll"}, "id": 129, "date": "2022-07-30T00:18:05+00:00", "user": {"id": 122, "name": "Red"}, "challenge_id": 196, "challenge": {"id": 196, "value": 50, "category": "osint", "name": "Everyone's A Critic 1"}, "type": "correct"}, {"team": {"id": 54, "name": "NestingDoll"}, "id": 154, "date": "2022-07-30T00:20:59+00:00", "user": {"id": 691, "name": "zaqk"}, "challenge_id": 181, "challenge": {"id": 181, "value": 50, "category": "osint", "name": "Everyone's A Critic 2"}, "type": "correct"}, {"team": {"id": 54, "name": "NestingDoll"}, "id": 183, "date": "2022-07-30T00:25:30+00:00", "user": {"id": 691, "name": "zaqk"}, "challenge_id": 211, "challenge": {"id": 211, "value": 50, "category": "osint", "name": "Everyone's A Critic 5"}, "type": "correct"}, {"team": {"id": 54, "name": "NestingDoll"}, "id": 257, "date": "2022-07-30T00:30:24+00:00", "user": {"id": 691, "name": "zaqk"}, "challenge_id": 182, "challenge": {"id": 182, "value": 50, "category": "osint", "name": "Everyone's A Critic 3"}, "type": "correct"}, {"team": {"id": 54, "name": "NestingDoll"}, "id": 286, "date": "2022-07-30T00:32:32+00:00", "user": {"id": 692, "name": "nomnom"}, "challenge_id": 208, "challenge": {"id": 208, "value": 50, "category": "jail", "name": "safepy"}, "type": "correct"}, {"team": {"id": 54, "name": "NestingDoll"}, "id": 295, "date": "2022-07-30T00:33:24+00:00", "user": {"id": 671, "name": "w0152"}, "challenge_id": 195, "challenge": {"id": 195, "value": 107, "category": "pwn", "name": "odd shell"}, "type": "correct"}, {"team": {"id": 54, "name": "NestingDoll"}, "id": 296, "date": "2022-07-30T00:33:33+00:00", "user": {"id": 159, "name": "BluP3gu1n"}, "challenge_id": 177, "challenge": {"id": 177, "value": 50, "category": "web", "name": "AR Pwny"}, "type": "correct"}, {"team": {"id": 54, "name": "NestingDoll"}, "id": 309, "date": "2022-07-30T00:34:39+00:00", "user": {"id": 122, "name": "Red"}, "challenge_id": 187, "challenge": {"id": 187, "value": 50, "category": "osint", "name": "Everyone's A Critic 4"}, "type": "correct"}, {"team": {"id": 54, "name": "NestingDoll"}, "id": 518, "date": "2022-07-30T01:02:14+00:00", "user": {"id": 692, "name": "nomnom"}, "challenge_id": 202, "challenge": {"id": 202, "value": 50, "category": "osint", "name": "Everyone's A Critic 6"}, "type": "correct"}, {"team": {"id": 54, "name": "NestingDoll"}, "id": 2404, "date": "2022-07-30T09:58:52+00:00", "user": {"id": 899, "name": "Linux_Enjoyer"}, "challenge_id": 178, "challenge": {"id": 178, "value": 85, "category": "crypto", "name": "asr"}, "type": "correct"}, {"team": {"id": 54, "name": "NestingDoll"}, "id": 3279, "date": "2022-07-30T16:20:56+00:00", "user": {"id": 671, "name": "w0152"}, "challenge_id": 207, "challenge": {"id": 207, "value": 139, "category": "crypto", "name": "Wringing Rings"}, "type": "correct"}, {"team": {"id": 54, "name": "NestingDoll"}, "id": 3670, "date": "2022-07-30T22:26:22+00:00", "user": {"id": 671, "name": "w0152"}, "challenge_id": 189, "challenge": {"id": 189, "value": 88, "category": "pwn", "name": "easy math 1"}, "type": "correct"}, {"team": {"id": 54, "name": "NestingDoll"}, "id": 4117, "date": "2022-07-31T08:01:53+00:00", "user": {"id": 140, "name": "kiddo"}, "challenge_id": 219, "challenge": {"id": 219, "value": 50, "category": "misc", "name": "Collection"}, "type": "correct"}, {"team": {"id": 54, "name": "NestingDoll"}, "id": 5030, "date": "2022-07-31T22:49:38+00:00", "user": {"id": 140, "name": "kiddo"}, "challenge_id": 220, "challenge": {"id": 220, "value": 100, "category": "misc", "name": "Feedback Survey"}, "type": "correct"}], "meta": {"count": 16}}
