{"success": true, "data": [{"team": {"id": 218, "name": "PLUS"}, "id": 808, "date": "2022-07-30T01:54:58+00:00", "user": {"id": 480, "name": "koi"}, "challenge_id": 196, "challenge": {"id": 196, "value": 50, "category": "osint", "name": "Everyone's A Critic 1"}, "type": "correct"}, {"team": {"id": 218, "name": "PLUS"}, "id": 856, "date": "2022-07-30T02:00:40+00:00", "user": {"id": 480, "name": "koi"}, "challenge_id": 182, "challenge": {"id": 182, "value": 50, "category": "osint", "name": "Everyone's A Critic 3"}, "type": "correct"}, {"team": {"id": 218, "name": "PLUS"}, "id": 1001, "date": "2022-07-30T02:40:50+00:00", "user": {"id": 480, "name": "koi"}, "challenge_id": 181, "challenge": {"id": 181, "value": 50, "category": "osint", "name": "Everyone's A Critic 2"}, "type": "correct"}, {"team": {"id": 218, "name": "PLUS"}, "id": 1609, "date": "2022-07-30T04:57:49+00:00", "user": {"id": 480, "name": "koi"}, "challenge_id": 173, "challenge": {"id": 173, "value": 50, "category": "crypto", "name": "Military Grade Encryption"}, "type": "correct"}, {"team": {"id": 218, "name": "PLUS"}, "id": 2069, "date": "2022-07-30T07:32:47+00:00", "user": {"id": 480, "name": "koi"}, "challenge_id": 187, "challenge": {"id": 187, "value": 50, "category": "osint", "name": "Everyone's A Critic 4"}, "type": "correct"}, {"team": {"id": 218, "name": "PLUS"}, "id": 2078, "date": "2022-07-30T07:37:08+00:00", "user": {"id": 480, "name": "koi"}, "challenge_id": 211, "challenge": {"id": 211, "value": 50, "category": "osint", "name": "Everyone's A Critic 5"}, "type": "correct"}, {"team": {"id": 218, "name": "PLUS"}, "id": 2174, "date": "2022-07-30T08:14:19+00:00", "user": {"id": 480, "name": "koi"}, "challenge_id": 193, "challenge": {"id": 193, "value": 371, "category": "misc", "name": "Sussy ML"}, "type": "correct"}, {"team": {"id": 218, "name": "PLUS"}, "id": 3265, "date": "2022-07-30T16:13:44+00:00", "user": {"id": 480, "name": "koi"}, "challenge_id": 176, "challenge": {"id": 176, "value": 332, "category": "crypto", "name": "mom can we have AES"}, "type": "correct"}, {"team": {"id": 218, "name": "PLUS"}, "id": 4473, "date": "2022-07-31T14:54:52+00:00", "user": {"id": 480, "name": "koi"}, "challenge_id": 215, "challenge": {"id": 215, "value": 332, "category": "jail", "name": "A Horse with No Neighs"}, "type": "correct"}, {"team": {"id": 218, "name": "PLUS"}, "id": 4485, "date": "2022-07-31T15:10:34+00:00", "user": {"id": 480, "name": "koi"}, "challenge_id": 202, "challenge": {"id": 202, "value": 50, "category": "osint", "name": "Everyone's A Critic 6"}, "type": "correct"}], "meta": {"count": 10}}
