{"success": true, "data": [{"team": {"id": 429, "name": "Trion"}, "id": 1656, "date": "2022-07-30T05:12:28+00:00", "user": {"id": 596, "name": "trion"}, "challenge_id": 208, "challenge": {"id": 208, "value": 50, "category": "jail", "name": "safepy"}, "type": "correct"}, {"team": {"id": 429, "name": "Trion"}, "id": 2066, "date": "2022-07-30T07:32:09+00:00", "user": {"id": 596, "name": "trion"}, "challenge_id": 187, "challenge": {"id": 187, "value": 50, "category": "osint", "name": "Everyone's A Critic 4"}, "type": "correct"}, {"team": {"id": 429, "name": "Trion"}, "id": 2072, "date": "2022-07-30T07:33:24+00:00", "user": {"id": 596, "name": "trion"}, "challenge_id": 196, "challenge": {"id": 196, "value": 50, "category": "osint", "name": "Everyone's A Critic 1"}, "type": "correct"}, {"team": {"id": 429, "name": "Trion"}, "id": 2076, "date": "2022-07-30T07:34:05+00:00", "user": {"id": 596, "name": "trion"}, "challenge_id": 181, "challenge": {"id": 181, "value": 50, "category": "osint", "name": "Everyone's A Critic 2"}, "type": "correct"}, {"team": {"id": 429, "name": "Trion"}, "id": 2127, "date": "2022-07-30T07:58:40+00:00", "user": {"id": 596, "name": "trion"}, "challenge_id": 211, "challenge": {"id": 211, "value": 50, "category": "osint", "name": "Everyone's A Critic 5"}, "type": "correct"}, {"team": {"id": 429, "name": "Trion"}, "id": 2134, "date": "2022-07-30T08:03:39+00:00", "user": {"id": 596, "name": "trion"}, "challenge_id": 202, "challenge": {"id": 202, "value": 50, "category": "osint", "name": "Everyone's A Critic 6"}, "type": "correct"}, {"team": {"id": 429, "name": "Trion"}, "id": 2163, "date": "2022-07-30T08:10:44+00:00", "user": {"id": 596, "name": "trion"}, "challenge_id": 182, "challenge": {"id": 182, "value": 50, "category": "osint", "name": "Everyone's A Critic 3"}, "type": "correct"}, {"team": {"id": 429, "name": "Trion"}, "id": 2166, "date": "2022-07-30T08:11:24+00:00", "user": {"id": 596, "name": "trion"}, "challenge_id": 203, "challenge": {"id": 203, "value": 1, "category": "misc", "name": "Join Discord"}, "type": "correct"}, {"team": {"id": 429, "name": "Trion"}, "id": 2352, "date": "2022-07-30T09:34:42+00:00", "user": {"id": 596, "name": "trion"}, "challenge_id": 193, "challenge": {"id": 193, "value": 371, "category": "misc", "name": "Sussy ML"}, "type": "correct"}, {"team": {"id": 429, "name": "Trion"}, "id": 2512, "date": "2022-07-30T10:42:14+00:00", "user": {"id": 596, "name": "trion"}, "challenge_id": 177, "challenge": {"id": 177, "value": 50, "category": "web", "name": "AR Pwny"}, "type": "correct"}, {"team": {"id": 429, "name": "Trion"}, "id": 2568, "date": "2022-07-30T11:04:58+00:00", "user": {"id": 596, "name": "trion"}, "challenge_id": 174, "challenge": {"id": 174, "value": 50, "category": "web", "name": "Frame"}, "type": "correct"}, {"team": {"id": 429, "name": "Trion"}, "id": 4201, "date": "2022-07-31T09:43:55+00:00", "user": {"id": 596, "name": "trion"}, "challenge_id": 175, "challenge": {"id": 175, "value": 332, "category": "misc", "name": "blackboxwarrior"}, "type": "correct"}, {"team": {"id": 429, "name": "Trion"}, "id": 4859, "date": "2022-07-31T20:28:27+00:00", "user": {"id": 596, "name": "trion"}, "challenge_id": 220, "challenge": {"id": 220, "value": 100, "category": "misc", "name": "Feedback Survey"}, "type": "correct"}, {"team": {"id": 429, "name": "Trion"}, "id": 4869, "date": "2022-07-31T20:33:15+00:00", "user": {"id": 596, "name": "trion"}, "challenge_id": 219, "challenge": {"id": 219, "value": 50, "category": "misc", "name": "Collection"}, "type": "correct"}], "meta": {"count": 14}}
